[{"course_code":"MODGRK AA","useful_title":"Elementary Modern Greek","course_score_mean":5.0,"rec_score_mean":5.0,"gem_probability_mean":0.125,"sentiment_score_median":0.9233,"best_gem_comment":"I would tell future students that this class is a gem! There is no pressure to master Greek, you just have to do your best and have fun in the class. It isn't your typical lecture style class, everything is very interactive which makes it more enjoyable to learn the language.","workload_score_mean":2.78,"best_gem_comment_short":"I would tell future students that this class is a gem!","course_id":"159840","link":"https:\/\/harvard.bluera.com\/harvard\/rpvf-eng.aspx?lang=eng&redi=1&SelectedIDforPrint=c7067c93e0444162146671a47c643629fdfd0eb22c7cbea912c4b9018101c25332be0dcaf03781440f10dffd55ae6352&ReportType=2&regl=en-US"}]